nsre/__init__.py
nsre/ast.py
nsre/lib.py
nsre/matchers.py
nsre/regexp.py
nsre/shortcuts.py
nsre-0.2.0.dist-info/LICENSE
nsre-0.2.0.dist-info/WHEEL
nsre-0.2.0.dist-info/METADATA
nsre-0.2.0.dist-info/RECORD
