Metadata-Version: 2.1
Name: nsre
Version: 0.2.0
Summary: Regular expressions for the 21st century. Match any data type.
Home-page: http://nsre.rtfd.io/
License: WTFPL
Keywords: regular expression
Author: Rémy Sanchez
Author-email: remy.sanchez@hyperthese.net
Requires-Python: >=3.6,<4.0
Classifier: License :: Other/Proprietary License
Classifier: Programming Language :: Python :: 3
Classifier: Programming Language :: Python :: 3.6
Classifier: Programming Language :: Python :: 3.7
Classifier: Programming Language :: Python :: 3.8
Requires-Dist: dataclasses (>=0.6,<0.7); python_version >= "3.6" and python_version < "3.7"
Requires-Dist: networkx (>=2.0,<3.0)
Project-URL: Repository, https://github.com/Xowap/nsre
